sqlalchemy_to_pydantic/__init__.py
sqlalchemy_to_pydantic/converter.py
sqlalchemy_to_pydantic-0.0.8.dist-info/LICENSE
sqlalchemy_to_pydantic-0.0.8.dist-info/METADATA
sqlalchemy_to_pydantic-0.0.8.dist-info/WHEEL
sqlalchemy_to_pydantic-0.0.8.dist-info/RECORD
