Metadata-Version: 2.1
Name: sqlalchemy-to-pydantic
Version: 0.0.8
Summary: Tools to convert SQLAlchemy models to Pydantic models
Author: Jack Zhai
Author-email: zhaijiawei0828@gmail.com
Requires-Python: >=3.10,<4.0
Classifier: Programming Language :: Python :: 3
Classifier: Programming Language :: Python :: 3.10
Classifier: Programming Language :: Python :: 3.11
Classifier: Programming Language :: Python :: 3.12
Requires-Dist: pydantic (>=2.3.0,<3.0.0)
Requires-Dist: sqlalchemy (>=2.0.20,<3.0.0)
